{
  "metadata": {
    "source": "Hawaii Department of Business, Economic Development and Tourism (DBEDT)",
    "destination": "Maui Island",
    "dataRange": "2021-03 to 2026-02",
    "unit": "persons (arrivals), $ million (expenditure), days (length of stay)"
  },
  "monthlyData": [
    { "month": "Mar 2021", "arrivals": 170766, "expenditure": 262.29, "lengthOfStay": 8.90 },
    { "month": "Apr 2021", "arrivals": 178579, "expenditure": 289.02, "lengthOfStay": 8.64 },
    { "month": "May 2021", "arrivals": 216413, "expenditure": 352.96, "lengthOfStay": 8.40 },
    { "month": "Jun 2021", "arrivals": 261045, "expenditure": 453.36, "lengthOfStay": 8.60 },
    { "month": "Jul 2021", "arrivals": 282736, "expenditure": 494.27, "lengthOfStay": 8.35 },
    { "month": "Aug 2021", "arrivals": 232992, "expenditure": 390.74, "lengthOfStay": 8.04 },
    { "month": "Sep 2021", "arrivals": 172762, "expenditure": 314.17, "lengthOfStay": 8.12 },
    { "month": "Oct 2021", "arrivals": 190210, "expenditure": 345.49, "lengthOfStay": 8.52 },
    { "month": "Nov 2021", "arrivals": 202919, "expenditure": 354.52, "lengthOfStay": 8.55 },
    { "month": "Dec 2021", "arrivals": 235880, "expenditure": 519.63, "lengthOfStay": 9.27 },
    { "month": "Jan 2022", "arrivals": 183436, "expenditure": 419.72, "lengthOfStay": 9.77 },
    { "month": "Feb 2022", "arrivals": 193149, "expenditure": 412.12, "lengthOfStay": 8.87 },
    { "month": "Mar 2022", "arrivals": 240257, "expenditure": 473.78, "lengthOfStay": 8.28 },
    { "month": "Apr 2022", "arrivals": 255433, "expenditure": 505.38, "lengthOfStay": 8.01 },
    { "month": "May 2022", "arrivals": 247329, "expenditure": 453.12, "lengthOfStay": 7.71 },
    { "month": "Jun 2022", "arrivals": 287878, "expenditure": 567.44, "lengthOfStay": 7.95 },
    { "month": "Jul 2022", "arrivals": 305862, "expenditure": 607.55, "lengthOfStay": 7.90 },
    { "month": "Aug 2022", "arrivals": 266176, "expenditure": 483.97, "lengthOfStay": 7.63 },
    { "month": "Sep 2022", "arrivals": 219667, "expenditure": 428.29, "lengthOfStay": 7.69 },
    { "month": "Oct 2022", "arrivals": 230512, "expenditure": 435.85, "lengthOfStay": 7.98 },
    { "month": "Nov 2022", "arrivals": 230380, "expenditure": 451.19, "lengthOfStay": 8.15 },
    { "month": "Dec 2022", "arrivals": 261080, "expenditure": 583.59, "lengthOfStay": 8.57 },
    { "month": "Jan 2023", "arrivals": 231644, "expenditure": 653.16, "lengthOfStay": 9.22 },
    { "month": "Feb 2023", "arrivals": 220988, "expenditure": 548.92, "lengthOfStay": 8.48 },
    { "month": "Mar 2023", "arrivals": 279014, "expenditure": 630.98, "lengthOfStay": 7.92 },
    { "month": "Apr 2023", "arrivals": 245080, "expenditure": 566.99, "lengthOfStay": 7.63 },
    { "month": "May 2023", "arrivals": 241293, "expenditure": 527.63, "lengthOfStay": 7.52 },
    { "month": "Jun 2023", "arrivals": 278654, "expenditure": 619.67, "lengthOfStay": 7.80 },
    { "month": "Jul 2023", "arrivals": 297082, "expenditure": 622.19, "lengthOfStay": 7.66 },
    { "month": "Aug 2023", "arrivals": 113771, "expenditure": 242.29, "lengthOfStay": 7.88 },
    { "month": "Sep 2023", "arrivals": 93027, "expenditure": 203.93, "lengthOfStay": 7.62 },
    { "month": "Oct 2023", "arrivals": 134493, "expenditure": 332.89, "lengthOfStay": 8.29 },
    { "month": "Nov 2023", "arrivals": 162470, "expenditure": 378.22, "lengthOfStay": 8.43 },
    { "month": "Dec 2023", "arrivals": 197520, "expenditure": 468.38, "lengthOfStay": 8.82 },
    { "month": "Jan 2024", "arrivals": 174471, "expenditure": 505.86, "lengthOfStay": 9.46 },
    { "month": "Feb 2024", "arrivals": 180193, "expenditure": 441.69, "lengthOfStay": 8.41 },
    { "month": "Mar 2024", "arrivals": 212005, "expenditure": 476.68, "lengthOfStay": 8.08 },
    { "month": "Apr 2024", "arrivals": 178645, "expenditure": 396.94, "lengthOfStay": 7.69 },
    { "month": "May 2024", "arrivals": 180128, "expenditure": 385.14, "lengthOfStay": 7.45 },
    { "month": "Jun 2024", "arrivals": 216083, "expenditure": 452.18, "lengthOfStay": 7.77 },
    { "month": "Jul 2024", "arrivals": 236245, "expenditure": 508.66, "lengthOfStay": 7.61 },
    { "month": "Aug 2024", "arrivals": 200598, "expenditure": 350.08, "lengthOfStay": 7.29 },
    { "month": "Sep 2024", "arrivals": 165322, "expenditure": 364.11, "lengthOfStay": 7.48 },
    { "month": "Oct 2024", "arrivals": 181487, "expenditure": 392.62, "lengthOfStay": 7.81 },
    { "month": "Nov 2024", "arrivals": 197803, "expenditure": 445.26, "lengthOfStay": 7.96 },
    { "month": "Dec 2024", "arrivals": 229290, "expenditure": 581.04, "lengthOfStay": 8.46 },
    { "month": "Jan 2025", "arrivals": 202416, "expenditure": 534.88, "lengthOfStay": 8.88 },
    { "month": "Feb 2025", "arrivals": 200205, "expenditure": 535.06, "lengthOfStay": 8.24 },
    { "month": "Mar 2025", "arrivals": 235672, "expenditure": 536.21, "lengthOfStay": 7.78 },
    { "month": "Apr 2025", "arrivals": 207590, "expenditure": 442.68, "lengthOfStay": 7.48 },
    { "month": "May 2025", "arrivals": 195334, "expenditure": 414.12, "lengthOfStay": 7.43 },
    { "month": "Jun 2025", "arrivals": 226981, "expenditure": 511.51, "lengthOfStay": 7.63 },
    { "month": "Jul 2025", "arrivals": 234805, "expenditure": 510.90, "lengthOfStay": 7.56 },
    { "month": "Aug 2025", "arrivals": 204990, "expenditure": 431.20, "lengthOfStay": 7.33 },
    { "month": "Sep 2025", "arrivals": 184201, "expenditure": 436.44, "lengthOfStay": 7.17 },
    { "month": "Oct 2025", "arrivals": 179459, "expenditure": 437.01, "lengthOfStay": 7.31 },
    { "month": "Nov 2025", "arrivals": 200823, "expenditure": 522.65, "lengthOfStay": 8.14 },
    { "month": "Dec 2025", "arrivals": 243687, "expenditure": 658.91, "lengthOfStay": 8.29 },
    { "month": "Jan 2026", "arrivals": 236180, "expenditure": 664.69, "lengthOfStay": 8.54 },
    { "month": "Feb 2026", "arrivals": 223227, "expenditure": 571.51, "lengthOfStay": 7.94 }
  ],
  "marketShare": {
    "Japan": 1520,
    "Canada": 21633,
    "Europe": 2359,
    "China": 1003
  },
  "monthlyStatistics": {
    "totalArrivals": 14750892,
    "peakMonth": "Jul 2022",
    "peakMonthArrivals": 305862,
    "lowestMonth": "Sep 2023",
    "lowestMonthArrivals": 93027,
    "averageLengthOfStay": 8.1
  }
}
